setup.cfg
setup.py
bin/spark-gce
spark_gce/__init__.py
spark_gce/spark_gce.py
spark_gce.egg-info/PKG-INFO
spark_gce.egg-info/SOURCES.txt
spark_gce.egg-info/dependency_links.txt
spark_gce.egg-info/requires.txt
spark_gce.egg-info/top_level.txt
spark_gce/support_files/copy-dir
spark_gce/support_files/growroot.sh
spark_gce/support_files/templates/ephemeral-hdfs/setup-auth.sh
spark_gce/support_files/templates/ephemeral-hdfs/setup-slave.sh
spark_gce/support_files/templates/ephemeral-hdfs/conf/core-site.xml
spark_gce/support_files/templates/ephemeral-hdfs/conf/hadoop-env.sh
spark_gce/support_files/templates/ephemeral-hdfs/conf/hadoop-metrics2.properties
spark_gce/support_files/templates/ephemeral-hdfs/conf/hdfs-site.xml
spark_gce/support_files/templates/ephemeral-hdfs/conf/mapred-site.xml
spark_gce/support_files/templates/ephemeral-hdfs/conf/masters
spark_gce/support_files/templates/ephemeral-hdfs/conf/slaves
spark_gce/support_files/templates/ganglia/000-default.conf
spark_gce/support_files/templates/ganglia/ganglia.conf
spark_gce/support_files/templates/ganglia/gmetad.conf
spark_gce/support_files/templates/ganglia/gmond.conf
spark_gce/support_files/templates/ganglia/ports.conf
spark_gce/support_files/templates/spark/setup-auth.sh
spark_gce/support_files/templates/spark/conf/core-site.xml
spark_gce/support_files/templates/spark/conf/spark-defaults.conf
spark_gce/support_files/templates/spark/conf/spark-env.sh