Metadata-Version: 1.1
Name: spark-gce
Version: 1.0.6
Summary: This script helps you create a Spark cluster on Google Compute Engine.
Home-page: https://github.com/broxtronix/spark-gce
Author: Michael Broxton
Author-email: broxton@gmail.com
License: UNKNOWN
Download-URL: https://github.com/broxtronix/spark-gce/tarball/1.0.6
Platform: UNKNOWN
